gitease/__init__.py
gitease/cli.py
gitease/git_helper.py
gitease/llm_helper.py
gitease/prompts/prompt_template.txt
gitease/prompts/undo_template.txt
gitease-0.0.11.dist-info/LICENSE
gitease-0.0.11.dist-info/METADATA
gitease-0.0.11.dist-info/WHEEL
gitease-0.0.11.dist-info/entry_points.txt
gitease-0.0.11.dist-info/RECORD
