Metadata-Version: 2.1
Name: gitease
Version: 0.0.11
Summary: A tool to simplfy git operations
License: BSD-3-Clause
Keywords: ai,llm,openai,developer-tools,git,nlp
Author: Yonatan Alexander
Author-email: yonatan@xethub.com
Maintainer: XetHub
Maintainer-email: contact@xethub.com
Requires-Python: >=3.8.1,<4.0.0
Classifier: Development Status :: 3 - Alpha
Classifier: License :: OSI Approved :: BSD License
Classifier: Operating System :: MacOS
Classifier: Operating System :: POSIX :: Linux
Classifier: Programming Language :: Python
Classifier: Programming Language :: Python :: 3
Classifier: Programming Language :: Python :: 3.9
Classifier: Programming Language :: Python :: 3.10
Classifier: Programming Language :: Python :: 3.11
Classifier: Programming Language :: Python :: 3 :: Only
Classifier: Programming Language :: Python :: 3.7
Classifier: Programming Language :: Python :: 3.8
Classifier: Programming Language :: Python :: Implementation :: CPython
Classifier: Programming Language :: Python :: Implementation :: PyPy
Classifier: Topic :: Scientific/Engineering :: Artificial Intelligence
Classifier: Topic :: Software Development :: Libraries :: Python Modules
Classifier: Topic :: Software Development :: Version Control :: Git
Classifier: Topic :: System :: Filesystems
Requires-Dist: gitpython (>=3.1.32,<4.0.0)
Requires-Dist: langchain (>=0.0.242,<0.0.243)
Requires-Dist: openai (>=0.27.8,<0.28.0)
Requires-Dist: pyperclip (>=1.8.2,<2.0.0)
Requires-Dist: rich (>=13.4.2,<14.0.0)
Requires-Dist: tiktoken (>=0.4.0,<0.5.0)
Requires-Dist: typer (>=0.9.0,<0.10.0)
